MofanJiqiXuexiJiaocheng2017510/README.md
MofanJiqiXuexiJiaocheng2017510/__init__.py
MofanJiqiXuexiJiaocheng2017510/__main__.py
MofanJiqiXuexiJiaocheng2017510/file.epub
MofanJiqiXuexiJiaocheng2017510/index.html
MofanJiqiXuexiJiaocheng2017510/css/__init__.py
MofanJiqiXuexiJiaocheng2017510/css/annotations.css
MofanJiqiXuexiJiaocheng2017510/css/main.css
MofanJiqiXuexiJiaocheng2017510/css/normalize.css
MofanJiqiXuexiJiaocheng2017510/css/popup.css
MofanJiqiXuexiJiaocheng2017510/font/__init__.py
MofanJiqiXuexiJiaocheng2017510/font/fontello.eot
MofanJiqiXuexiJiaocheng2017510/font/fontello.svg
MofanJiqiXuexiJiaocheng2017510/font/fontello.ttf
MofanJiqiXuexiJiaocheng2017510/font/fontello.woff
MofanJiqiXuexiJiaocheng2017510/img/__init__.py
MofanJiqiXuexiJiaocheng2017510/img/annotator-glyph-sprite.png
MofanJiqiXuexiJiaocheng2017510/img/annotator-icon-sprite.png
MofanJiqiXuexiJiaocheng2017510/img/apple-touch-icon.png
MofanJiqiXuexiJiaocheng2017510/img/cancelfullscreen.png
MofanJiqiXuexiJiaocheng2017510/img/close.png
MofanJiqiXuexiJiaocheng2017510/img/fullscreen.png
MofanJiqiXuexiJiaocheng2017510/img/loader.gif
MofanJiqiXuexiJiaocheng2017510/img/menu-icon.png
MofanJiqiXuexiJiaocheng2017510/img/save.png
MofanJiqiXuexiJiaocheng2017510/img/saved.png
MofanJiqiXuexiJiaocheng2017510/img/settings-s.png
MofanJiqiXuexiJiaocheng2017510/img/settings.png
MofanJiqiXuexiJiaocheng2017510/img/star.png
MofanJiqiXuexiJiaocheng2017510/js/__init__.py
MofanJiqiXuexiJiaocheng2017510/js/epub.js
MofanJiqiXuexiJiaocheng2017510/js/epub.min.js
MofanJiqiXuexiJiaocheng2017510/js/epub.min.map
MofanJiqiXuexiJiaocheng2017510/js/hooks.min.js
MofanJiqiXuexiJiaocheng2017510/js/hooks.min.map
MofanJiqiXuexiJiaocheng2017510/js/reader.js
MofanJiqiXuexiJiaocheng2017510/js/reader.js.map
MofanJiqiXuexiJiaocheng2017510/js/reader.min.js
MofanJiqiXuexiJiaocheng2017510/js/reader.min.map
MofanJiqiXuexiJiaocheng2017510/js/hooks/__init__.py
MofanJiqiXuexiJiaocheng2017510/js/hooks/extensions/__init__.py
mofan_jiqi_xuexi_jiaocheng_2017_5_10-2024.3.2.0.dist-info/METADATA
mofan_jiqi_xuexi_jiaocheng_2017_5_10-2024.3.2.0.dist-info/WHEEL
mofan_jiqi_xuexi_jiaocheng_2017_5_10-2024.3.2.0.dist-info/entry_points.txt
mofan_jiqi_xuexi_jiaocheng_2017_5_10-2024.3.2.0.dist-info/top_level.txt
mofan_jiqi_xuexi_jiaocheng_2017_5_10-2024.3.2.0.dist-info/RECORD
